{"blocks": {"standard": [{"stateLabels": "reward", "edgeDisplay": "never", "layout": {"1": [2, 2], "2": [3, 2], "3": [2, 1], "4": [1, 2], "5": [2, 3], "6": [4, 2], "7": [2, 0], "8": [0, 2], "9": [2, 4], "10": [4, 1], "11": [4, 3], "12": [1, 0], "13": [3, 0], "14": [0, 1], "15": [0, 3], "16": [1, 4], "17": [3, 4]}, "graph": {"1": {"up": [11, 3], "left": [7, 4], "right": [-12, 2], "down": [14, 5]}, "2": {"right": [16, 6]}, "3": {"up": [3, 7]}, "4": {"left": [15, 8]}, "5": {"down": [10, 9]}, "6": {"up": [5, 10], "down": [-4, 11]}, "7": {"left": [-16, 12], "right": [1, 13]}, "8": {"up": [18, 14], "down": [18, 15]}, "9": {"left": [-19, 16], "right": [-13, 17]}, "10": {}, "11": {}, "12": {}, "13": {}, "14": {}, "15": {}, "16": {}, "17": {}}, "initial": 1, "stateDisplay": "click", "path": {"1": null, "2": 1, "3": 2, "4": 3, "5": 4, "6": [[1], [1]], "7": [[2], [2]], "8": [[3], [3]], "9": [[4], [4]], "10": [[1], [1], [2]], "11": [[1], [1], [4]], "12": [[2], [2], [3]], "13": [[2], [2], [1]], "14": [[3], [3], [2]], "15": [[3], [3], [4]], "16": [[4], [4], [3]], "17": [[4], [4], [1]]}, "trial_i": 0, "stateRewards": {"1": 0, "2": -12, "3": 11, "4": 7, "5": 14, "6": 16, "7": 3, "8": 15, "9": 10, "10": 5, "11": -4, "12": -16, "13": 1, "14": 18, "15": 18, "16": -19, "17": -13}}, {"stateLabels": "reward", "edgeDisplay": "never", "layout": {"1": [2, 2], "2": [3, 2], "3": [2, 1], "4": [1, 2], "5": [2, 3], "6": [4, 2], "7": [2, 0], "8": [0, 2], "9": [2, 4], "10": [4, 1], "11": [4, 3], "12": [1, 0], "13": [3, 0], "14": [0, 1], "15": [0, 3], "16": [1, 4], "17": [3, 4]}, "graph": {"1": {"up": [17, 3], "left": [0, 4], "right": [-18, 2], "down": [10, 5]}, "2": {"right": [16, 6]}, "3": {"up": [17, 7]}, "4": {"left": [5, 8]}, "5": {"down": [18, 9]}, "6": {"up": [11, 10], "down": [5, 11]}, "7": {"left": [-12, 12], "right": [-12, 13]}, "8": {"up": [1, 14], "down": [10, 15]}, "9": {"left": [18, 16], "right": [-17, 17]}, "10": {}, "11": {}, "12": {}, "13": {}, "14": {}, "15": {}, "16": {}, "17": {}}, "initial": 1, "stateDisplay": "click", "path": {"1": null, "2": 1, "3": 2, "4": 3, "5": 4, "6": [[1], [1]], "7": [[2], [2]], "8": [[3], [3]], "9": [[4], [4]], "10": [[1], [1], [2]], "11": [[1], [1], [4]], "12": [[2], [2], [3]], "13": [[2], [2], [1]], "14": [[3], [3], [2]], "15": [[3], [3], [4]], "16": [[4], [4], [3]], "17": [[4], [4], [1]]}, "trial_i": 1, "stateRewards": {"1": 0, "2": -18, "3": 17, "4": 0, "5": 10, "6": 16, "7": 17, "8": 5, "9": 18, "10": 11, "11": 5, "12": -12, "13": -12, "14": 1, "15": 10, "16": 18, "17": -17}}, {"stateLabels": "reward", "edgeDisplay": "never", "layout": {"1": [2, 2], "2": [3, 2], "3": [2, 1], "4": [1, 2], "5": [2, 3], "6": [4, 2], "7": [2, 0], "8": [0, 2], "9": [2, 4], "10": [4, 1], "11": [4, 3], "12": [1, 0], "13": [3, 0], "14": [0, 1], "15": [0, 3], "16": [1, 4], "17": [3, 4]}, "graph": {"1": {"up": [-12, 3], "left": [7, 4], "right": [7, 2], "down": [10, 5]}, "2": {"right": [10, 6]}, "3": {"up": [17, 7]}, "4": {"left": [15, 8]}, "5": {"down": [-13, 9]}, "6": {"up": [17, 10], "down": [15, 11]}, "7": {"left": [11, 12], "right": [9, 13]}, "8": {"up": [-11, 14], "down": [-13, 15]}, "9": {"left": [8, 16], "right": [8, 17]}, "10": {}, "11": {}, "12": {}, "13": {}, "14": {}, "15": {}, "16": {}, "17": {}}, "initial": 1, "stateDisplay": "click", "path": {"1": null, "2": 1, "3": 2, "4": 3, "5": 4, "6": [[1], [1]], "7": [[2], [2]], "8": [[3], [3]], "9": [[4], [4]], "10": [[1], [1], [2]], "11": [[1], [1], [4]], "12": [[2], [2], [3]], "13": [[2], [2], [1]], "14": [[3], [3], [2]], "15": [[3], [3], [4]], "16": [[4], [4], [3]], "17": [[4], [4], [1]]}, "trial_i": 2, "stateRewards": {"1": 0, "2": 7, "3": -12, "4": 7, "5": 10, "6": 10, "7": 17, "8": 15, "9": -13, "10": 17, "11": 15, "12": 11, "13": 9, "14": -11, "15": -13, "16": 8, "17": 8}}, {"stateLabels": "reward", "edgeDisplay": "never", "layout": {"1": [2, 2], "2": [3, 2], "3": [2, 1], "4": [1, 2], "5": [2, 3], "6": [4, 2], "7": [2, 0], "8": [0, 2], "9": [2, 4], "10": [4, 1], "11": [4, 3], "12": [1, 0], "13": [3, 0], "14": [0, 1], "15": [0, 3], "16": [1, 4], "17": [3, 4]}, "graph": {"1": {"up": [9, 3], "left": [-4, 4], "right": [9, 2], "down": [12, 5]}, "2": {"right": [8, 6]}, "3": {"up": [-8, 7]}, "4": {"left": [13, 8]}, "5": {"down": [8, 9]}, "6": {"up": [17, 10], "down": [-16, 11]}, "7": {"left": [0, 12], "right": [5, 13]}, "8": {"up": [-3, 14], "down": [18, 15]}, "9": {"left": [-13, 16], "right": [-19, 17]}, "10": {}, "11": {}, "12": {}, "13": {}, "14": {}, "15": {}, "16": {}, "17": {}}, "initial": 1, "stateDisplay": "click", "path": {"1": null, "2": 1, "3": 2, "4": 3, "5": 4, "6": [[1], [1]], "7": [[2], [2]], "8": [[3], [3]], "9": [[4], [4]], "10": [[1], [1], [2]], "11": [[1], [1], [4]], "12": [[2], [2], [3]], "13": [[2], [2], [1]], "14": [[3], [3], [2]], "15": [[3], [3], [4]], "16": [[4], [4], [3]], "17": [[4], [4], [1]]}, "trial_i": 3, "stateRewards": {"1": 0, "2": 9, "3": 9, "4": -4, "5": 12, "6": 8, "7": -8, "8": 13, "9": 8, "10": 17, "11": -16, "12": 0, "13": 5, "14": -3, "15": 18, "16": -13, "17": -19}}, {"stateLabels": "reward", "edgeDisplay": "never", "layout": {"1": [2, 2], "2": [3, 2], "3": [2, 1], "4": [1, 2], "5": [2, 3], "6": [4, 2], "7": [2, 0], "8": [0, 2], "9": [2, 4], "10": [4, 1], "11": [4, 3], "12": [1, 0], "13": [3, 0], "14": [0, 1], "15": [0, 3], "16": [1, 4], "17": [3, 4]}, "graph": {"1": {"up": [3, 3], "left": [17, 4], "right": [-2, 2], "down": [10, 5]}, "2": {"right": [10, 6]}, "3": {"up": [3, 7]}, "4": {"left": [9, 8]}, "5": {"down": [14, 9]}, "6": {"up": [15, 10], "down": [-6, 11]}, "7": {"left": [17, 12], "right": [7, 13]}, "8": {"up": [-9, 14], "down": [-17, 15]}, "9": {"left": [-9, 16], "right": [18, 17]}, "10": {}, "11": {}, "12": {}, "13": {}, "14": {}, "15": {}, "16": {}, "17": {}}, "initial": 1, "stateDisplay": "click", "path": {"1": null, "2": 1, "3": 2, "4": 3, "5": 4, "6": [[1], [1]], "7": [[2], [2]], "8": [[3], [3]], "9": [[4], [4]], "10": [[1], [1], [2]], "11": [[1], [1], [4]], "12": [[2], [2], [3]], "13": [[2], [2], [1]], "14": [[3], [3], [2]], "15": [[3], [3], [4]], "16": [[4], [4], [3]], "17": [[4], [4], [1]]}, "trial_i": 4, "stateRewards": {"1": 0, "2": -2, "3": 3, "4": 17, "5": 10, "6": 10, "7": 3, "8": 9, "9": 14, "10": 15, "11": -6, "12": 17, "13": 7, "14": -9, "15": -17, "16": -9, "17": 18}}, {"stateLabels": "reward", "edgeDisplay": "never", "layout": {"1": [2, 2], "2": [3, 2], "3": [2, 1], "4": [1, 2], "5": [2, 3], "6": [4, 2], "7": [2, 0], "8": [0, 2], "9": [2, 4], "10": [4, 1], "11": [4, 3], "12": [1, 0], "13": [3, 0], "14": [0, 1], "15": [0, 3], "16": [1, 4], "17": [3, 4]}, "graph": {"1": {"up": [17, 3], "left": [13, 4], "right": [9, 2], "down": [10, 5]}, "2": {"right": [14, 6]}, "3": {"up": [-10, 7]}, "4": {"left": [5, 8]}, "5": {"down": [-5, 9]}, "6": {"up": [-16, 10], "down": [-16, 11]}, "7": {"left": [-4, 12], "right": [-4, 13]}, "8": {"up": [16, 14], "down": [-13, 15]}, "9": {"left": [12, 16], "right": [10, 17]}, "10": {}, "11": {}, "12": {}, "13": {}, "14": {}, "15": {}, "16": {}, "17": {}}, "initial": 1, "stateDisplay": "click", "path": {"1": null, "2": 1, "3": 2, "4": 3, "5": 4, "6": [[1], [1]], "7": [[2], [2]], "8": [[3], [3]], "9": [[4], [4]], "10": [[1], [1], [2]], "11": [[1], [1], [4]], "12": [[2], [2], [3]], "13": [[2], [2], [1]], "14": [[3], [3], [2]], "15": [[3], [3], [4]], "16": [[4], [4], [3]], "17": [[4], [4], [1]]}, "trial_i": 5, "stateRewards": {"1": 0, "2": 9, "3": 17, "4": 13, "5": 10, "6": 14, "7": -10, "8": 5, "9": -5, "10": -16, "11": -16, "12": -4, "13": -4, "14": 16, "15": -13, "16": 12, "17": 10}}, {"stateLabels": "reward", "edgeDisplay": "never", "layout": {"1": [2, 2], "2": [3, 2], "3": [2, 1], "4": [1, 2], "5": [2, 3], "6": [4, 2], "7": [2, 0], "8": [0, 2], "9": [2, 4], "10": [4, 1], "11": [4, 3], "12": [1, 0], "13": [3, 0], "14": [0, 1], "15": [0, 3], "16": [1, 4], "17": [3, 4]}, "graph": {"1": {"up": [9, 3], "left": [5, 4], "right": [3, 2], "down": [10, 5]}, "2": {"right": [18, 6]}, "3": {"up": [0, 7]}, "4": {"left": [-8, 8]}, "5": {"down": [12, 9]}, "6": {"up": [-8, 10], "down": [17, 11]}, "7": {"left": [-2, 12], "right": [1, 13]}, "8": {"up": [14, 14], "down": [10, 15]}, "9": {"left": [-9, 16], "right": [-13, 17]}, "10": {}, "11": {}, "12": {}, "13": {}, "14": {}, "15": {}, "16": {}, "17": {}}, "initial": 1, "stateDisplay": "click", "path": {"1": null, "2": 1, "3": 2, "4": 3, "5": 4, "6": [[1], [1]], "7": [[2], [2]], "8": [[3], [3]], "9": [[4], [4]], "10": [[1], [1], [2]], "11": [[1], [1], [4]], "12": [[2], [2], [3]], "13": [[2], [2], [1]], "14": [[3], [3], [2]], "15": [[3], [3], [4]], "16": [[4], [4], [3]], "17": [[4], [4], [1]]}, "trial_i": 6, "stateRewards": {"1": 0, "2": 3, "3": 9, "4": 5, "5": 10, "6": 18, "7": 0, "8": -8, "9": 12, "10": -8, "11": 17, "12": -2, "13": 1, "14": 14, "15": 10, "16": -9, "17": -13}}, {"stateLabels": "reward", "edgeDisplay": "never", "layout": {"1": [2, 2], "2": [3, 2], "3": [2, 1], "4": [1, 2], "5": [2, 3], "6": [4, 2], "7": [2, 0], "8": [0, 2], "9": [2, 4], "10": [4, 1], "11": [4, 3], "12": [1, 0], "13": [3, 0], "14": [0, 1], "15": [0, 3], "16": [1, 4], "17": [3, 4]}, "graph": {"1": {"up": [9, 3], "left": [-6, 4], "right": [13, 2], "down": [6, 5]}, "2": {"right": [4, 6]}, "3": {"up": [1, 7]}, "4": {"left": [11, 8]}, "5": {"down": [10, 9]}, "6": {"up": [-8, 10], "down": [-14, 11]}, "7": {"left": [9, 12], "right": [-4, 13]}, "8": {"up": [18, 14], "down": [12, 15]}, "9": {"left": [18, 16], "right": [18, 17]}, "10": {}, "11": {}, "12": {}, "13": {}, "14": {}, "15": {}, "16": {}, "17": {}}, "initial": 1, "stateDisplay": "click", "path": {"1": null, "2": 1, "3": 2, "4": 3, "5": 4, "6": [[1], [1]], "7": [[2], [2]], "8": [[3], [3]], "9": [[4], [4]], "10": [[1], [1], [2]], "11": [[1], [1], [4]], "12": [[2], [2], [3]], "13": [[2], [2], [1]], "14": [[3], [3], [2]], "15": [[3], [3], [4]], "16": [[4], [4], [3]], "17": [[4], [4], [1]]}, "trial_i": 7, "stateRewards": {"1": 0, "2": 13, "3": 9, "4": -6, "5": 6, "6": 4, "7": 1, "8": 11, "9": 10, "10": -8, "11": -14, "12": 9, "13": -4, "14": 18, "15": 12, "16": 18, "17": 18}}, {"stateLabels": "reward", "edgeDisplay": "never", "layout": {"1": [2, 2], "2": [3, 2], "3": [2, 1], "4": [1, 2], "5": [2, 3], "6": [4, 2], "7": [2, 0], "8": [0, 2], "9": [2, 4], "10": [4, 1], "11": [4, 3], "12": [1, 0], "13": [3, 0], "14": [0, 1], "15": [0, 3], "16": [1, 4], "17": [3, 4]}, "graph": {"1": {"up": [13, 3], "left": [11, 4], "right": [5, 2], "down": [14, 5]}, "2": {"right": [12, 6]}, "3": {"up": [11, 7]}, "4": {"left": [13, 8]}, "5": {"down": [16, 9]}, "6": {"up": [11, 10], "down": [1, 11]}, "7": {"left": [17, 12], "right": [11, 13]}, "8": {"up": [-13, 14], "down": [8, 15]}, "9": {"left": [-17, 16], "right": [-13, 17]}, "10": {}, "11": {}, "12": {}, "13": {}, "14": {}, "15": {}, "16": {}, "17": {}}, "initial": 1, "stateDisplay": "click", "path": {"1": null, "2": 1, "3": 2, "4": 3, "5": 4, "6": [[1], [1]], "7": [[2], [2]], "8": [[3], [3]], "9": [[4], [4]], "10": [[1], [1], [2]], "11": [[1], [1], [4]], "12": [[2], [2], [3]], "13": [[2], [2], [1]], "14": [[3], [3], [2]], "15": [[3], [3], [4]], "16": [[4], [4], [3]], "17": [[4], [4], [1]]}, "trial_i": 8, "stateRewards": {"1": 0, "2": 5, "3": 13, "4": 11, "5": 14, "6": 12, "7": 11, "8": 13, "9": 16, "10": 11, "11": 1, "12": 17, "13": 11, "14": -13, "15": 8, "16": -17, "17": -13}}, {"stateLabels": "reward", "edgeDisplay": "never", "layout": {"1": [2, 2], "2": [3, 2], "3": [2, 1], "4": [1, 2], "5": [2, 3], "6": [4, 2], "7": [2, 0], "8": [0, 2], "9": [2, 4], "10": [4, 1], "11": [4, 3], "12": [1, 0], "13": [3, 0], "14": [0, 1], "15": [0, 3], "16": [1, 4], "17": [3, 4]}, "graph": {"1": {"up": [17, 3], "left": [15, 4], "right": [-6, 2], "down": [-1, 5]}, "2": {"right": [16, 6]}, "3": {"up": [7, 7]}, "4": {"left": [13, 8]}, "5": {"down": [6, 9]}, "6": {"up": [7, 10], "down": [7, 11]}, "7": {"left": [13, 12], "right": [7, 13]}, "8": {"up": [-19, 14], "down": [1, 15]}, "9": {"left": [-1, 16], "right": [2, 17]}, "10": {}, "11": {}, "12": {}, "13": {}, "14": {}, "15": {}, "16": {}, "17": {}}, "initial": 1, "stateDisplay": "click", "path": {"1": null, "2": 1, "3": 2, "4": 3, "5": 4, "6": [[1], [1]], "7": [[2], [2]], "8": [[3], [3]], "9": [[4], [4]], "10": [[1], [1], [2]], "11": [[1], [1], [4]], "12": [[2], [2], [3]], "13": [[2], [2], [1]], "14": [[3], [3], [2]], "15": [[3], [3], [4]], "16": [[4], [4], [3]], "17": [[4], [4], [1]]}, "trial_i": 9, "stateRewards": {"1": 0, "2": -6, "3": 17, "4": 15, "5": -1, "6": 16, "7": 7, "8": 13, "9": 6, "10": 7, "11": 7, "12": 13, "13": 7, "14": -19, "15": 1, "16": -1, "17": 2}}, {"stateLabels": "reward", "edgeDisplay": "never", "layout": {"1": [2, 2], "2": [3, 2], "3": [2, 1], "4": [1, 2], "5": [2, 3], "6": [4, 2], "7": [2, 0], "8": [0, 2], "9": [2, 4], "10": [4, 1], "11": [4, 3], "12": [1, 0], "13": [3, 0], "14": [0, 1], "15": [0, 3], "16": [1, 4], "17": [3, 4]}, "graph": {"1": {"up": [3, 3], "left": [3, 4], "right": [9, 2], "down": [-3, 5]}, "2": {"right": [2, 6]}, "3": {"up": [13, 7]}, "4": {"left": [0, 8]}, "5": {"down": [6, 9]}, "6": {"up": [11, 10], "down": [0, 11]}, "7": {"left": [-12, 12], "right": [-12, 13]}, "8": {"up": [16, 14], "down": [4, 15]}, "9": {"left": [-3, 16], "right": [1, 17]}, "10": {}, "11": {}, "12": {}, "13": {}, "14": {}, "15": {}, "16": {}, "17": {}}, "initial": 1, "stateDisplay": "click", "path": {"1": null, "2": 1, "3": 2, "4": 3, "5": 4, "6": [[1], [1]], "7": [[2], [2]], "8": [[3], [3]], "9": [[4], [4]], "10": [[1], [1], [2]], "11": [[1], [1], [4]], "12": [[2], [2], [3]], "13": [[2], [2], [1]], "14": [[3], [3], [2]], "15": [[3], [3], [4]], "16": [[4], [4], [3]], "17": [[4], [4], [1]]}, "trial_i": 10, "stateRewards": {"1": 0, "2": 9, "3": 3, "4": 3, "5": -3, "6": 2, "7": 13, "8": 0, "9": 6, "10": 11, "11": 0, "12": -12, "13": -12, "14": 16, "15": 4, "16": -3, "17": 1}}, {"stateLabels": "reward", "edgeDisplay": "never", "layout": {"1": [2, 2], "2": [3, 2], "3": [2, 1], "4": [1, 2], "5": [2, 3], "6": [4, 2], "7": [2, 0], "8": [0, 2], "9": [2, 4], "10": [4, 1], "11": [4, 3], "12": [1, 0], "13": [3, 0], "14": [0, 1], "15": [0, 3], "16": [1, 4], "17": [3, 4]}, "graph": {"1": {"up": [9, 3], "left": [3, 4], "right": [17, 2], "down": [10, 5]}, "2": {"right": [6, 6]}, "3": {"up": [15, 7]}, "4": {"left": [5, 8]}, "5": {"down": [-1, 9]}, "6": {"up": [1, 10], "down": [15, 11]}, "7": {"left": [-8, 12], "right": [1, 13]}, "8": {"up": [8, 14], "down": [-1, 15]}, "9": {"left": [10, 16], "right": [10, 17]}, "10": {}, "11": {}, "12": {}, "13": {}, "14": {}, "15": {}, "16": {}, "17": {}}, "initial": 1, "stateDisplay": "click", "path": {"1": null, "2": 1, "3": 2, "4": 3, "5": 4, "6": [[1], [1]], "7": [[2], [2]], "8": [[3], [3]], "9": [[4], [4]], "10": [[1], [1], [2]], "11": [[1], [1], [4]], "12": [[2], [2], [3]], "13": [[2], [2], [1]], "14": [[3], [3], [2]], "15": [[3], [3], [4]], "16": [[4], [4], [3]], "17": [[4], [4], [1]]}, "trial_i": 11, "stateRewards": {"1": 0, "2": 17, "3": 9, "4": 3, "5": 10, "6": 6, "7": 15, "8": 5, "9": -1, "10": 1, "11": 15, "12": -8, "13": 1, "14": 8, "15": -1, "16": 10, "17": 10}}]}, "params": {"creation_date": "2017-06-26 20:46:00.524752"}, "conditions": [{"PR_type": 2, "info_cost": 0.01}, {"PR_type": 2, "info_cost": 1.6}, {"PR_type": 2, "info_cost": 2.8}]}